ptzipcam/__init__.py
ptzipcam/camera.py
ptzipcam/convert.py
ptzipcam/io.py
ptzipcam/logs.py
ptzipcam/ptz_camera.py
ptzipcam/tracker.py
ptzipcam/ui.py
ptzipcam/video_writer.py
ptzipcam-0.1.0.dist-info/LICENSE
ptzipcam-0.1.0.dist-info/METADATA
ptzipcam-0.1.0.dist-info/WHEEL
ptzipcam-0.1.0.dist-info/top_level.txt
ptzipcam-0.1.0.dist-info/RECORD
