Metadata-Version: 2.1
Name: ptzipcam
Version: 0.1.0
Summary: Package for controlling PTZ IP cameras that support ONVIF
Author: Ian Ingram
License: MIT
Classifier: Programming Language :: Python :: 3
Classifier: License :: OSI Approved :: MIT License
Classifier: Development Status :: 2 - Pre-Alpha
Classifier: Operating System :: POSIX :: Linux
License-File: LICENSE
Requires-Dist: numpy
Requires-Dist: opencv-python
Requires-Dist: onvif-zeep
Requires-Dist: camml
